{
    "lang": "fr",
    "joumouaaTime": "13:00",
    "aidTime": "",
    "imsakNbMinBeforeSobh": 0,
    "minimumIchaTime": "19:00",
    "maximumIchaTimeForNoWaiting": "",
    "prayersWaitingTimes": [20, 10, 10, 7, 10],
    "prayerTimesAdjustment": [20, 0, 0, 0, -6],
    "prayerTimesFixing": ["", "", "", "", ""],
    "hijriAdjustment": 0,
    "hijriDateEnabled": true,
    "douaaAfterAdhanEnabled": true,
    "douaaAfterPrayerEnabled": true,
    "androidAppEnabled": false,
    "calculChoice": "custom",
    "city": "null",
    "prayerMethod": "ISNA",
    "latitude": 48.92,
    "longitude": 2.25,
    "fajrDegree": "",
    "ichaaDegree": "",
    "iqamaDisplayTime": 45,
    "adhanDouaaDisplayTime": 30,
    "headerText": "Mosquée Audra - Colombes",
    "site": "Horaires de prière sur mobile et tablette <span style=\"color: #1b6d85;\">http://audra-colombes.horaires-de-priere.fr</span>",
    "supportTel": "+33629111641",
    "supportEmail": "horaires-priere@binary-consulting.fr",
    "footerText": "Association Courte échelle"
}
